setup.py
zabbixcli
zabbixcli-worker
zabbixcli.egg-info/PKG-INFO
zabbixcli.egg-info/SOURCES.txt
zabbixcli.egg-info/dependency_links.txt
zabbixcli.egg-info/requires.txt
zabbixcli.egg-info/top_level.txt
zabbixlib/__init__.py
zabbixlib/app.py
zabbixlib/autoreg.py
zabbixlib/cli.py
zabbixlib/defaults.py
zabbixlib/discovery.py
zabbixlib/graph.py
zabbixlib/group.py
zabbixlib/item.py
zabbixlib/macro.py
zabbixlib/object.py
zabbixlib/template.py
zabbixlib/trigger.py
zabbixlib/trigger_action.py