Metadata-Version: 1.0
Name: zabbixcli
Version: 1.0.4
Summary: Tool for manage zabbix templates as YAML files.
Home-page: https://github.com/blacked/zabbixcli
Author: Alexey Dubkov
Author-email: alexey.dubkov@gmail.com
License: UNKNOWN
Platform: UNKNOWN
